minerva_cli/__init__.py
minerva_cli/_version.py
minerva_cli/minerva.py
minerva_cli/util/__init__.py
minerva_cli/util/configurer.py
test/__init__.py
test/mocks.py
minerva_cli-0.0.3.dist-info/LICENSE
minerva_cli-0.0.3.dist-info/METADATA
minerva_cli-0.0.3.dist-info/WHEEL
minerva_cli-0.0.3.dist-info/dependency_links.txt
minerva_cli-0.0.3.dist-info/entry_points.txt
minerva_cli-0.0.3.dist-info/top_level.txt
minerva_cli-0.0.3.dist-info/RECORD
