Metadata-Version: 2.1
Name: minerva-cli
Version: 0.0.3
Summary: Minerva Command Line Interface
Home-page: https://github.com/labsyspharm/minerva-cli
Author: Juha Ruokonen
License: UNKNOWN
Platform: UNKNOWN
Classifier: Programming Language :: Python :: 3
Classifier: License :: OSI Approved :: MIT License
Classifier: Operating System :: OS Independent
Requires-Python: >=3.7
Requires-Dist: boto3 (>=1.14.44)
Requires-Dist: requests
Requires-Dist: tabulate
Requires-Dist: minerva-lib (==0.0.5)
Requires-Dist: tqdm
